{
  "env": "staging",
  "buildtime": {
    "origin_server": {
      "ip": "0.0.0.0",
      "port": "5000",
      "https": {
        "enabled": false,
        "crt": "",
        "key": ""
      }
    },
    "debug": true,
    "hot": false,
    "sourcemap": false,
    "uglify": true,
    "analyze": false
  },
  "runtime": {
    "api": {
      "host": "https://backend-test.codemao.cn",
      "port": "443"
    },
    "education": {
      "host": "https://staging-api-education-codemaster.codemao.cn",
      "port": ""
    },
    "time": {
      "host": "https://staging-time.codemao.cn",
      "port": ""
    },
    "host": {
      "event_track": "https://collection.codemao.cn/report/{product_code}",
      "mlz_host": "https://staging-mlz.codemao.cn",
      "ide": "https://staging-ide.codemao.cn",
      "box": "https://staging-box-v2.codemao.cn",
      "box2": "https://staging-box-v2.codemao.cn",
      "wood": "https://staging-wood.codemao.cn",
      "lizzy": "https://staging-lizzy.codemao.cn/",
      "tob": "https://tob-staging.codemao.cn"
    }
  }
}